graspologic_native-1.2.5.dist-info/METADATA
graspologic_native-1.2.5.dist-info/WHEEL
graspologic_native/__init__.py
graspologic_native/__init__.pyi
graspologic_native/py.typed
graspologic_native/graspologic_native.abi3.so
graspologic_native-1.2.5.dist-info/RECORD
