Metadata-Version: 2.1
Name: graspologic-native
Version: 1.2.5
Classifier: Development Status :: 5 - Production/Stable
Classifier: License :: OSI Approved :: MIT License
Classifier: Programming Language :: Python :: Implementation :: CPython
Classifier: Programming Language :: Python :: 3.8
Classifier: Programming Language :: Python :: 3.9
Classifier: Programming Language :: Python :: 3.10
Classifier: Programming Language :: Python :: 3.11
Classifier: Programming Language :: Python :: 3.12
Classifier: Programming Language :: Python :: 3.13
Classifier: Topic :: Scientific/Engineering :: Mathematics
Summary: Python native companion module to the graspologic library
Author: daxpryce@microsoft.com
Author-email: Dax Pryce <daxpryce@microsoft.com>
Maintainer-email: Dax Pryce <daxpryce@microsoft.com>
License: MIT
Requires-Python: >=3.8, <3.14
Project-URL: Github, https://github.com/graspologic-org/graspologic-native
Project-URL: Graspologic, https://github.com/graspologic-org/graspologic
